ysolive/__init__.py
ysolive-0.0.1.dist-info/METADATA
ysolive-0.0.1.dist-info/WHEEL
ysolive-0.0.1.dist-info/top_level.txt
ysolive-0.0.1.dist-info/RECORD
